clickstream/__init__.py
clickstream/schema.avsc
clickstream/schema_classes.py
clickstream/io/__init__.py
clickstream/io/streammachine/__init__.py
clickstream/io/streammachine/public_schemas/__init__.py
clickstream/io/streammachine/public_schemas/clickstream/__init__.py
streammachine_schemas_clickstream_avro-0.2.0.dist-info/METADATA
streammachine_schemas_clickstream_avro-0.2.0.dist-info/WHEEL
streammachine_schemas_clickstream_avro-0.2.0.dist-info/top_level.txt
streammachine_schemas_clickstream_avro-0.2.0.dist-info/RECORD
