Metadata-Version: 2.1
Name: streammachine-schemas-clickstream-avro
Version: 0.2.0
Summary: Python classes for clickstream
Home-page: UNKNOWN
Author: Stream Machine B.V.
Author-email: apis@streammachine.io
License: UNKNOWN
Keywords: streammachine api client driver schema
Platform: UNKNOWN
Classifier: Programming Language :: Python :: 3.6
Classifier: Programming Language :: Python :: 3.7
Classifier: Programming Language :: Python :: 3.8
Classifier: Intended Audience :: Developers
Classifier: Operating System :: OS Independent
Classifier: Topic :: Internet :: WWW/HTTP
Requires-Python: >=3.6
Requires-Dist: streammachine-schemas-common (==0.0.3)
Requires-Dist: avro-gen (==0.3.0)
Requires-Dist: tzlocal (==2.1)
